domo_actors/__init__.py
domo_actors/actors/__init__.py
domo_actors/actors/actor.py
domo_actors/actors/actor_protocol.py
domo_actors/actors/actor_proxy.py
domo_actors/actors/address.py
domo_actors/actors/array_mailbox.py
domo_actors/actors/bounded_mailbox.py
domo_actors/actors/dead_letters.py
domo_actors/actors/deferred_promise.py
domo_actors/actors/definition.py
domo_actors/actors/directory.py
domo_actors/actors/environment.py
domo_actors/actors/execution_context.py
domo_actors/actors/life_cycle.py
domo_actors/actors/local_stage.py
domo_actors/actors/logger.py
domo_actors/actors/mailbox.py
domo_actors/actors/message.py
domo_actors/actors/observable_state.py
domo_actors/actors/protocol.py
domo_actors/actors/root_actors.py
domo_actors/actors/scheduler.py
domo_actors/actors/stage.py
domo_actors/actors/stage_internal.py
domo_actors/actors/supervised.py
domo_actors/actors/supervisor.py
domo_actors/actors/testkit/__init__.py
domo_actors/actors/testkit/test_await_assist.py
domo_actors/actors/testkit/test_dead_letters_listener.py
domo_actors-1.0.0.dist-info/licenses/LICENSE.md
domo_actors-1.0.0.dist-info/METADATA
domo_actors-1.0.0.dist-info/WHEEL
domo_actors-1.0.0.dist-info/top_level.txt
domo_actors-1.0.0.dist-info/RECORD
