Metadata-Version: 2.4
Name: domo-actors
Version: 1.0.0
Summary: DomoActors-Py Actor Model Toolkit for Python
Author-email: Vaughn Vernon <vaughn@kalele.io>
License-Expression: RPL-1.5
Project-URL: Homepage, https://github.com/VaughnVernon/DomoActors-Py
Project-URL: Documentation, https://github.com/VaughnVernon/DomoActors-Py/blob/main/README.md
Project-URL: Repository, https://github.com/VaughnVernon/DomoActors-Py
Project-URL: Issues, https://github.com/VaughnVernon/DomoActors-Py/issues
Keywords: actor,actors,actor-model,concurrency,async,distributed
Classifier: Development Status :: 4 - Beta
Classifier: Intended Audience :: Developers
Classifier: Programming Language :: Python :: 3
Classifier: Programming Language :: Python :: 3.10
Classifier: Programming Language :: Python :: 3.11
Classifier: Programming Language :: Python :: 3.12
Classifier: Topic :: Software Development :: Libraries
Classifier: Topic :: System :: Distributed Computing
Requires-Python: >=3.10
License-File: LICENSE.md
Provides-Extra: dev
Requires-Dist: pytest>=7.0.0; extra == "dev"
Requires-Dist: pytest-asyncio>=0.21.0; extra == "dev"
Requires-Dist: black>=23.0.0; extra == "dev"
Requires-Dist: mypy>=1.0.0; extra == "dev"
Requires-Dist: ruff>=0.1.0; extra == "dev"
Dynamic: license-file
